sidlingvo/__init__.py
sidlingvo/attentive_scoring_layer.py
sidlingvo/attentive_scoring_layer_test.py
sidlingvo/cumulative_statistics_layer.py
sidlingvo/cumulative_statistics_layer_test.py
sidlingvo/fe_utils.py
sidlingvo/fe_utils_test.py
sidlingvo/language_map.py
sidlingvo/loss_layers.py
sidlingvo/loss_layers_test.py
sidlingvo/utils.py
sidlingvo/utils_test.py
sidlingvo/wav_to_dvector.py
sidlingvo/wav_to_lang.py
sidlingvo-0.1.0.dist-info/METADATA
sidlingvo-0.1.0.dist-info/WHEEL
sidlingvo-0.1.0.dist-info/top_level.txt
sidlingvo-0.1.0.dist-info/RECORD
