Metadata-Version: 2.1
Name: sidlingvo
Version: 0.1.0
Summary: Lingvo utils for Google SVL team
Home-page: https://github.com/google/speaker-id/tree/master/lingvo
Author: Quan Wang
Author-email: quanw@google.com
Classifier: Programming Language :: Python :: 3
Classifier: License :: OSI Approved :: Apache Software License
Classifier: Operating System :: OS Independent
Requires-Dist: numpy
Requires-Dist: scipy
Requires-Dist: lingvo
Requires-Dist: tensorflow-text
Requires-Dist: librosa
Requires-Dist: colortimelog
